exactonline_prefect_tasks/__init__.py
exactonline_prefect_tasks/_version.py
exactonline_prefect_tasks/api.py
exactonline_prefect_tasks/exactonline_api.py
exactonline_prefect_tasks/utils.py
exactonline_prefect_tasks/aws/__init__.py
exactonline_prefect_tasks/aws/s3_client.py
exactonline_prefect_tasks/aws/s3_storage.py
exactonline_prefect_tasks/aws/secretsmanager_client.py
exactonline_prefect_tasks/aws/secretsmanager_storage.py
exactonline_prefect_tasks/exceptions/__init__.py
exactonline_prefect_tasks/exceptions/api_exception.py
exactonline_prefect_tasks/exceptions/auth_exception.py
exactonline_prefect_tasks/exceptions/missing_parameters_exception.py
exactonline_prefect_tasks/exceptions/no_record_found_exception.py
exactonline_prefect_tasks/tasks/__init__.py
exactonline_prefect_tasks/tasks/create.py
exactonline_prefect_tasks/tasks/delete.py
exactonline_prefect_tasks/tasks/get_all.py
exactonline_prefect_tasks/tasks/get_by_id.py
exactonline_prefect_tasks/tasks/read.py
exactonline_prefect_tasks/tasks/search.py
exactonline_prefect_tasks/tasks/update.py
exactonline_prefect_tasks/tasks/xml_upload.py
exactonline_prefect_tasks-0.0.26.dist-info/LICENSE
exactonline_prefect_tasks-0.0.26.dist-info/METADATA
exactonline_prefect_tasks-0.0.26.dist-info/WHEEL
exactonline_prefect_tasks-0.0.26.dist-info/top_level.txt
exactonline_prefect_tasks-0.0.26.dist-info/RECORD
