Metadata-Version: 2.1
Name: exactonline-prefect-tasks
Version: 0.0.26
Home-page: https://github.com/aporacloudmobile/exactonline_prefect_tasks
Author: Carlos Paiva
Author-email: carlospaiva87@gmail.com
Classifier: Programming Language :: Python :: 3
Classifier: Operating System :: OS Independent
Requires-Python: >=3.6
License-File: LICENSE
Requires-Dist: requests (<2.27.0)
Requires-Dist: jsonmerge (>=1.8.0)
Requires-Dist: versioneer (>=0.22)
Requires-Dist: setuptools (>=61.3.1)
Requires-Dist: pytest (>=7.1.1)
Requires-Dist: prefect (==0.15.11)
Requires-Dist: exactonline (>=0.3.6)
Requires-Dist: boto3 (>=1.21.32)
Requires-Dist: botocore (>=1.24.32)
